compareworkbooks/__init__.py
compareworkbooks/__main__.py
compareworkbooks/core/__init__.py
compareworkbooks/core/difference.py
compareworkbooks/tests/__init__.py
compareworkbooks/tests/test_1984.py
compareworkbooks-0.2.3.dist-info/LICENSE.txt
compareworkbooks-0.2.3.dist-info/METADATA
compareworkbooks-0.2.3.dist-info/WHEEL
compareworkbooks-0.2.3.dist-info/top_level.txt
compareworkbooks-0.2.3.dist-info/RECORD
