Metadata-Version: 2.2
Name: compareworkbooks
Version: 0.2.3
Summary: This project compares workbooks with openpyxl.
Author-email: Johannes Horler <johannes.horler@charite.de>
License: The MIT License (MIT)
Project-URL: Documentation, https://pypi.org/project/compareworkbooks/
Project-URL: Download, https://pypi.org/project/compareworkbooks/#files
Project-URL: Index, https://pypi.org/project/compareworkbooks/
Project-URL: Source, https://github.com/johanneshorler/compareworkbooks/
Classifier: Development Status :: 3 - Alpha
Classifier: License :: OSI Approved :: MIT License
Classifier: Natural Language :: English
Classifier: Operating System :: OS Independent
Classifier: Programming Language :: Python
Classifier: Programming Language :: Python :: 3
Classifier: Programming Language :: Python :: 3 :: Only
Requires-Python: >=3.8
License-File: LICENSE.txt
Requires-Dist: openpyxl>=3.1.3
